bytetracker/__init__.py
bytetracker/basetrack.py
bytetracker/byte_tracker.py
bytetracker/kalman_filter.py
bytetracker/matching.py
bytetracker/config/__init__.py
bytetracker_gml-0.3.2.dist-info/LICENSE
bytetracker_gml-0.3.2.dist-info/METADATA
bytetracker_gml-0.3.2.dist-info/WHEEL
bytetracker_gml-0.3.2.dist-info/top_level.txt
bytetracker_gml-0.3.2.dist-info/RECORD
