Metadata-Version: 2.1
Name: bytetracker-gml
Version: 0.3.2
Summary: Packaged version of the ByteTrack repository
Home-page: https://github.com/kadirnar/bytetrack-pip
Author: Gimlet Labs
License: MIT
Keywords: machine-learning,deep-learning,pytorch,vision,image-classification,object-detection,object-tracking,tracker,bytetrack
Classifier: Development Status :: 5 - Production/Stable
Classifier: Operating System :: OS Independent
Classifier: Intended Audience :: Developers
Classifier: Intended Audience :: Science/Research
Classifier: Programming Language :: Python :: 3
Classifier: Programming Language :: Python :: 3.7
Classifier: Programming Language :: Python :: 3.8
Classifier: Programming Language :: Python :: 3.9
Classifier: Topic :: Software Development :: Libraries
Classifier: Topic :: Software Development :: Libraries :: Python Modules
Classifier: Topic :: Education
Classifier: Topic :: Scientific/Engineering
Classifier: Topic :: Scientific/Engineering :: Artificial Intelligence
Requires-Python: >=3.5
License-File: LICENSE
Requires-Dist: lapx ==0.5.8
Requires-Dist: scipy >=1.9.3
Requires-Dist: torch >=1.13.0
